{"cameraMode":{"drawMode":0,"name":"Shaded","section":"Shading Mode"},"sceneLighting":false,"audioPlay":false,"sceneViewState":{"m_AlwaysRefresh":false,"showFog":true,"showSkybox":false,"showFlares":true,"showImageEffects":true,"showParticleSystems":true,"showVisualEffectGraphs":true,"m_FxEnabled":true},"in2DMode":false,"pivot":{"x":0.0,"y":0.0,"z":-0.7999999523162842},"rotation":{"x":-0.14535044133663178,"y":-0.32042643427848818,"z":0.05059583857655525,"w":-0.9348139762878418},"size":0.17320509254932404,"orthographic":false}